yoyo/__init__.py
yoyo/__main__.py
yoyo/backends.py
yoyo/compat.py
yoyo/config.py
yoyo/connections.py
yoyo/exceptions.py
yoyo/migrations.py
yoyo/utils.py
yoyo/internalmigrations/__init__.py
yoyo/internalmigrations/v1.py
yoyo/internalmigrations/v2.py
yoyo/scripts/__init__.py
yoyo/scripts/main.py
yoyo/scripts/migrate.py
yoyo/scripts/newmigration.py
yoyox-2023.3.16.0.dist-info/LICENSE.txt
yoyox-2023.3.16.0.dist-info/METADATA
yoyox-2023.3.16.0.dist-info/WHEEL
yoyox-2023.3.16.0.dist-info/top_level.txt
yoyox-2023.3.16.0.dist-info/RECORD
