Metadata-Version: 2.1
Name: yoyox
Version: 2023.3.16.0
Summary: A fork of yoyo that's designed to support the 3.10+ python versions, you probably shoul not use this
Author-email: Chris Halbersma <chris@halbersma.us>
Project-URL: Homepage, https://github.com/pypa/sampleproject
Project-URL: Bug Tracker, https://github.com/pypa/sampleproject/issues
Classifier: Programming Language :: Python :: 3
Classifier: Environment :: Console
Classifier: License :: OSI Approved :: Apache Software License
Classifier: Topic :: Software Development :: Version Control
Requires-Python: >=3.8
License-File: LICENSE.txt
